docs/source/conf.py
epydemix/__init__.py
epydemix/calibration/__init__.py
epydemix/calibration/abc.py
epydemix/calibration/calibration_results.py
epydemix/calibration/metrics.py
epydemix/model/__init__.py
epydemix/model/epimodel.py
epydemix/model/predefined_models.py
epydemix/model/simulation_output.py
epydemix/model/simulation_results.py
epydemix/model/transition.py
epydemix/population/__init__.py
epydemix/population/population.py
epydemix/utils/__init__.py
epydemix/utils/abc_smc_utils.py
epydemix/utils/utils.py
epydemix/visualization/__init__.py
epydemix/visualization/plotting.py
epydemix-1.0.1.dist-info/licenses/LICENSE
tests/__init__.py
tests/conftest.py
tests/test_abc.py
tests/test_epimodel.py
tests/test_metrics.py
tests/test_plotting.py
tests/test_population.py
tests/test_predefined_models.py
tests/test_tutorial1.py
tests/test_tutorial2.py
tests/test_tutorial3.py
tests/test_tutorial4.py
tests/test_tutorial5.py
tests/test_tutorial6.py
tests/fixtures/__init__.py
tutorials/external_models/my_stochastic_sir.py
validation/models/stochastic_seir.py
validation/models/stochastic_seir_population.py
validation/models/stochastic_sir.py
validation/models/stochastic_sir_population.py
validation/models/stochastic_sis.py
validation/models/stochastic_sis_population.py
epydemix-1.0.1.dist-info/METADATA
epydemix-1.0.1.dist-info/WHEEL
epydemix-1.0.1.dist-info/top_level.txt
epydemix-1.0.1.dist-info/RECORD
