Metadata-Version: 2.4
Name: epydemix
Version: 1.0.1
Summary: A Python package for epidemic modeling, simulation, and calibration
Home-page: https://github.com/epistorm/epydemix
Author: The Epydemix Developers
Author-email: Nicolò Gozzi <nic.gozzi@gmail.com>, Corrado Gioannini <corrado.gioannini@isi.it>, Luca Rossi <luca.rossi@isi.it>, Nicola Perra <nicolaperra@gmail.com>, Alessandro Vespignani <a.vespignani@northeastern.edu>
License:                     GNU GENERAL PUBLIC LICENSE
Project-URL: homepage, https://epydemix.org
Project-URL: repository, https://github.com/epistorm/epydemix
Project-URL: documentation, https://epydemix.readthedocs.io/en/latest/
Requires-Python: >=3.8
License-File: LICENSE
Requires-Dist: evalidate>=2.0.3
Requires-Dist: matplotlib>=3.7.3
Requires-Dist: numpy>=1.23.5
Requires-Dist: pandas>=2.0.3
Requires-Dist: scipy>=1.10.1
Requires-Dist: seaborn>=0.13.2
Requires-Dist: setuptools>=68.2.0
Dynamic: author
Dynamic: home-page
Dynamic: license-file
Dynamic: requires-python
